shen/__init__.py
shen/cli.py
shen/core/__init__.py
shen/core/app.py
shen/core/config.py
shen/core/plugin_manager.py
shen/mcp/__init__.py
shen/plugins/__init__.py
shen/utils/__init__.py
shen/utils/logging.py
shen_cli-0.0.0b0.dist-info/LICENSE
shen_cli-0.0.0b0.dist-info/METADATA
shen_cli-0.0.0b0.dist-info/WHEEL
shen_cli-0.0.0b0.dist-info/entry_points.txt
shen_cli-0.0.0b0.dist-info/RECORD
