Metadata-Version: 2.3
Name: shen-cli
Version: 0.0.0b0
Summary: An AI-powered CLI tool for automating non-programming daily tasks
License: MIT
Keywords: cli,ai,automation,productivity,mcp
Author: Shen Jingnan
Requires-Python: >=3.9,<4.0
Classifier: Development Status :: 3 - Alpha
Classifier: Intended Audience :: End Users/Desktop
Classifier: License :: OSI Approved :: MIT License
Classifier: Operating System :: OS Independent
Classifier: Programming Language :: Python :: 3
Classifier: Programming Language :: Python :: 3.9
Classifier: Programming Language :: Python :: 3.10
Classifier: Programming Language :: Python :: 3.11
Classifier: Programming Language :: Python :: 3.12
Classifier: Programming Language :: Python :: 3.13
Classifier: Topic :: Utilities
Requires-Dist: click (>=8.1.7,<9.0.0)
Requires-Dist: pydantic (>=2.5.0,<3.0.0)
Requires-Dist: pydantic-settings (>=2.1.0,<3.0.0)
Requires-Dist: rich (>=13.7.0,<14.0.0)
Project-URL: Homepage, https://github.com/shenjingnan/shen
Project-URL: Repository, https://github.com/shenjingnan/shen
